.gitignore
CHANGELOG.md
LICENSE
README.md
README.ru.md
requirements.txt
setup.py
client_payment_sdk/__init__.py
client_payment_sdk/client.py
client_payment_sdk/enums.py
client_payment_sdk/exceptions.py
client_payment_sdk/model_test.py
client_payment_sdk/models.py
client_payment_sdk/sign.py
client_payment_sdk/t1.py
client_payment_sdk/t2.py
client_payment_sdk/test.py
client_payment_sdk/utils.py
client_payment_sdk/webhook.py
client_payment_sdk.egg-info/PKG-INFO
client_payment_sdk.egg-info/SOURCES.txt
client_payment_sdk.egg-info/dependency_links.txt
client_payment_sdk.egg-info/not-zip-safe
client_payment_sdk.egg-info/requires.txt
client_payment_sdk.egg-info/top_level.txt
examples/payment.py
examples/payment_3ds.py
examples/payment_balance.py
examples/payment_h2h.py
examples/payment_sbp.py
examples/payment_status.py
examples/webhook.py
examples/withdrawal.py
examples/withdrawal_status.py
tests/payment.py