Metadata-Version: 2.1
Name: client-payment-sdk
Version: 0.0.1
Summary: Client Payment Python SDK
Home-page: https://github.com/Space-Around/client-payment-sdk-python.git
Author: SpaceAround101
Author-email: viksnamax@mail.ru
License: MIT license
Download-URL: https://github.com/Space-Around/client-payment-sdk-python.git/tarball/0.0.1
Platform: UNKNOWN
Classifier: Development Status :: 5 - Production/Stable
Classifier: Intended Audience :: Developers
Classifier: License :: OSI Approved :: MIT License
Classifier: Programming Language :: Python :: 3.10
Classifier: Topic :: Software Development :: Libraries :: Python Modules
Requires: requests (>=2.9.1)
Requires: jwcrypto (>=1.0)
Requires: setuptools (>=57.0.0)
License-File: LICENSE
